uwsgi_tasks/__init__.py
uwsgi_tasks/decorators.py
uwsgi_tasks/tasks.py
uwsgi_tasks/tests.py
uwsgi_tasks/utils.py
uwsgi_tasks-0.7.3.dist-info/LICENSE
uwsgi_tasks-0.7.3.dist-info/METADATA
uwsgi_tasks-0.7.3.dist-info/WHEEL
uwsgi_tasks-0.7.3.dist-info/top_level.txt
uwsgi_tasks-0.7.3.dist-info/RECORD
