Metadata-Version: 2.1
Name: uwsgi-tasks
Version: 0.7.3
Summary: Asynchronous tasks management with UWSGI server
Home-page: https://github.com/Bahus/uwsgi_tasks
Author: Oleg Churkin
Author-email: bahusoff@gmail.com
License: MIT
Keywords: asynchronous,tasks,uwsgi
Platform: Platform Independent
Classifier: Development Status :: 5 - Production/Stable
Classifier: Environment :: Web Environment
Classifier: Operating System :: OS Independent
Classifier: Programming Language :: Python
Classifier: Programming Language :: Python :: 2.7
Classifier: Programming Language :: Python :: 3
Classifier: Topic :: Software Development :: Libraries :: Python Modules
Classifier: Intended Audience :: Developers
Classifier: License :: OSI Approved :: MIT License
Requires: uwsgi
Requires: six
Requires-Dist: six
